jpterm.py
jmespath_community_terminal-1.1.1.data/scripts/jpterm
jmespath_community_terminal-1.1.1.dist-info/LICENSE
jmespath_community_terminal-1.1.1.dist-info/METADATA
jmespath_community_terminal-1.1.1.dist-info/NOTICE
jmespath_community_terminal-1.1.1.dist-info/WHEEL
jmespath_community_terminal-1.1.1.dist-info/top_level.txt
jmespath_community_terminal-1.1.1.dist-info/RECORD
