Metadata-Version: 2.1
Name: jmespath-community-terminal
Version: 1.1.1
Summary: JMESPath Terminal
Home-page: https://github.com/jmespath-community/jmespath.terminal
Author: James Saryerwinnie, Springcomp
Author-email: js@jamesls.com, springcomp@users.noreply.github.com
Classifier: Development Status :: 5 - Production/Stable
Classifier: Intended Audience :: Developers
Classifier: Natural Language :: English
Classifier: License :: OSI Approved :: Apache Software License
Classifier: Programming Language :: Python
Classifier: Programming Language :: Python :: 2.6
Classifier: Programming Language :: Python :: 2.7
Classifier: Programming Language :: Python :: 3
Classifier: Programming Language :: Python :: 3.3
License-File: LICENSE
License-File: NOTICE
Requires-Dist: jmespath-community (>=1.1.0)
Requires-Dist: Pygments (<3.0,>=2.14.0)
Requires-Dist: urwid (==2.1.2)
